bib_dedupe/__init__.py
bib_dedupe/bib_dedupe.py
bib_dedupe/block.py
bib_dedupe/cli.py
bib_dedupe/cluster.py
bib_dedupe/constants/__init__.py
bib_dedupe/constants/colors.py
bib_dedupe/constants/entrytypes.py
bib_dedupe/constants/fields.py
bib_dedupe/debug.py
bib_dedupe/dedupe_benchmark.py
bib_dedupe/journal_variants.csv
bib_dedupe/match.py
bib_dedupe/match_conditions.py
bib_dedupe/maybe_cases.py
bib_dedupe/merge.py
bib_dedupe/prep.py
bib_dedupe/prep_abstract.py
bib_dedupe/prep_author.py
bib_dedupe/prep_container_title.py
bib_dedupe/prep_doi.py
bib_dedupe/prep_number.py
bib_dedupe/prep_pages.py
bib_dedupe/prep_title.py
bib_dedupe/prep_volume.py
bib_dedupe/prep_year.py
bib_dedupe/sim.py
bib_dedupe/util.py
bib_dedupe-0.10.0.dist-info/LICENSE
bib_dedupe-0.10.0.dist-info/METADATA
bib_dedupe-0.10.0.dist-info/WHEEL
bib_dedupe-0.10.0.dist-info/entry_points.txt
bib_dedupe-0.10.0.dist-info/RECORD
