Metadata-Version: 2.1
Name: bib-dedupe
Version: 0.10.0
Summary: Identify and merge duplicates in bibliographic records
Home-page: https://github.com/CoLRev-Environment/bib-dedupe
License: MIT
Keywords: de-duplication,duplicate,meta-analysis,research,reproducible research,open science,literature,literature review,systematic review,systematic literature review
Author: Gerit Wagner
Author-email: gerit.wagner@uni-bamberg.de
Requires-Python: >=3.10,<4.0
Classifier: Development Status :: 4 - Beta
Classifier: License :: OSI Approved :: MIT License
Classifier: Natural Language :: English
Classifier: Operating System :: OS Independent
Classifier: Programming Language :: Python :: 3
Classifier: Programming Language :: Python :: 3.10
Classifier: Programming Language :: Python :: 3.11
Classifier: Programming Language :: Python :: 3.12
Classifier: Programming Language :: Python :: 3.13
Classifier: Topic :: Scientific/Engineering
Classifier: Typing :: Typed
Provides-Extra: dev
Provides-Extra: with-data
Requires-Dist: asreview (>=1.5,<2.0) ; extra == "with-data"
Requires-Dist: coverage[toml] (>=7.3.2,<8.0.0) ; extra == "dev"
Requires-Dist: number-parser (>=0.3.2,<0.4.0)
Requires-Dist: numpy (>=2.1.2,<3.0.0)
Requires-Dist: pandas (>=2.2.3,<3.0.0) ; extra == "with-data"
Requires-Dist: pylint (==3.0.1) ; extra == "dev"
Requires-Dist: pytest (>=7.2.1,<8.0.0) ; extra == "dev"
Requires-Dist: rapidfuzz (>=3.10.0,<4.0.0)
Requires-Dist: requests (>=2.32.3,<3.0.0)
Requires-Dist: tqdm (>=4.66.1,<5.0.0)
Project-URL: Documentation, https://colrev-environment.github.io/bib-dedupe/
Project-URL: Repository, https://github.com/CoLRev-Environment/bib-dedupe
